senseair_s8/__init__.py
senseair_s8/__main__.py
senseair_s8/senseair_s8.py
senseair_s8-0.1.0.dist-info/LICENSE
senseair_s8-0.1.0.dist-info/METADATA
senseair_s8-0.1.0.dist-info/WHEEL
senseair_s8-0.1.0.dist-info/RECORD
