Metadata-Version: 2.3
Name: senseair-s8
Version: 0.1.0
Summary: Python library for interfacing with a Senseair S8 CO2 sensor.
License: MIT
Keywords: senseair,co2,sensor,python
Author: Nick Doornekamp
Author-email: nddoornekamp@gmail.com
Requires-Python: >=3.6
Classifier: Programming Language :: Python :: 3
Classifier: License :: OSI Approved :: MIT License
Classifier: Intended Audience :: Developers
Classifier: Topic :: Software Development :: Libraries :: Python Modules
Requires-Dist: pyserial (>=3.5,<4.0)
